{
  "build": "py38_0",
  "build_number": 0,
  "channel": "https://repo.anaconda.com/pkgs/main/osx-64",
  "constrains": [],
  "depends": [
    "ipykernel",
    "ipython_genutils",
    "jinja2",
    "jupyter_client >=5.3.4",
    "jupyter_core >=4.6.1",
    "nbconvert",
    "nbformat",
    "prometheus_client",
    "python >=3.8,<3.9.0a0",
    "pyzmq >=17",
    "send2trash",
    "terminado >=0.8.1",
    "tornado >=5.0",
    "traitlets >=4.2.1"
  ],
  "features": "",
  "fn": "notebook-6.0.3-py38_0.conda",
  "legacy_bz2_md5": "616946ba9bdf12ab7b118dd0d5dd9799",
  "legacy_bz2_size": 6648802,
  "license": "BSD-3-Clause",
  "license_family": "BSD",
  "md5": "5c53ba88e0e1868d509ff34f480e46b5",
  "name": "notebook",
  "sha256": "3a1877430605da9bd2025aa793636435c1679b9fefa87f76779713e53434e83a",
  "size": 4163724,
  "subdir": "osx-64",
  "timestamp": 1580229226882,
  "track_features": "",
  "url": "https://repo.anaconda.com/pkgs/main/osx-64/notebook-6.0.3-py38_0.conda",
  "version": "6.0.3"
}